gradio_paramviewer/__init__.py
gradio_paramviewer/paramviewer.py
gradio_paramviewer/paramviewer.pyi
gradio_paramviewer/templates/component/index.js
gradio_paramviewer/templates/component/style.css
gradio_paramviewer/templates/example/index.js
gradio_paramviewer/templates/example/style.css
gradio_paramviewer-0.0.4.dist-info/METADATA
gradio_paramviewer-0.0.4.dist-info/WHEEL
gradio_paramviewer-0.0.4.dist-info/RECORD
